pld2/pldrom_test3.vhd
-- pldrom.vhd
library ieee;
use ieee.std_logic_1164.all;
use ieee.numeric_std.all;

entity pldrom is
    Port (
		  addr : in std_logic_vector (3 downto 0);
		  data : out std_logic_vector (9 downto 0)	
	 );
end pldrom;

architecture Behavioral of pldrom is 
begin
		data <=
			"00011110000" when addr = "0000" else -- (0) load 16 into the LR
			"0100100100" when addr = "0001" else -- (1) subtract 1 from the LR
			"0110000001" when addr = "0010" else -- (2) check if LR is 0, branch to (5) if true
			"1000000001" when addr = "0011" else -- (3) if not 0, jump back to (1) to continue subtracting
			"0001111111" when addr = "0100" else -- (4) load all 1s into the LR for flashing
			"0111101100" when addr = "0101" else -- (5) toggle LR between all 1s and 0s (start of flash sequence)
			"0101101100" when addr = "0110" else -- (6) toggle LR between all 1s and 0s
			"0101101100" when addr = "0111" else -- (7) toggle LR between all 1s and 0s
			"0101101100" when addr = "1000" else -- (8) toggle LR between all 1s and 0s
			"0101101100" when addr = "1001" else -- (9) toggle LR between all 1s and 0s
			"0101101100" when addr = "1010" else -- (10) toggle LR between all 1s and 0s
			"0101101100" when addr = "1011" else -- (11) toggle LR between all 1s and 0s
			"0101101100" when addr = "1100" else -- (12) toggle LR between all 1s and 0s
			"0101101100" when addr = "1101" else -- (13) toggle LR between all 1s and 0s (end of flash sequence)
			"1000000000" when addr = "1110" else -- (14) jump to instruction 0 to restart the process
			"1111111111";                        -- (15) garbage/default
		  
end Behavioral;

pld2/pld2.vhd
library ieee;
use ieee.std_logic_1164.all;
use ieee.numeric_std.all; 

entity pld2 is

	port(
		clk	 : in	std_logic;
		reset	 : in	std_logic;
		lightsig : out	std_logic_vector(7 downto 0);
		IRView : out std_logic_vector(9 downto 0)
		--PCView : out std_logic_vector(3 downto 0)
	);

end entity;

architecture rtl of pld2 is

	component pldrom
		port 
		(
			--address of instruction to return
			addr : in std_logic_vector(3 downto 0);
			--instruction to be executed
			data : out std_logic_vector (9 downto 0)
		);
	end component;

	--Build an enumerated type for the state machine
	type state_type is (sFetch, sExecute1, sExecute2);

	--Register to hold the current state
	signal state : state_type;
	
	signal IR   : std_logic_vector(9 downto 0);
	signal PC	: UNSIGNED(3 downto 0);
	signal LR	: UNSIGNED(7 downto 0);
	signal ROMvalue : std_logic_vector(9 downto 0);
	
	signal ACC	: UNSIGNED(7 downto 0);
	signal SRC	: UNSIGNED(7 downto 0);

	

begin

	-- Logic to advance to the next state
	process (clk, reset)
	begin
		if reset = '0' then
			state <= sFetch;
			PC <= (others => '0');
			IR <= "0000000000";
			LR <= (others => '0');
		elsif (rising_edge(clk)) then
			case state is
				when sFetch=>
					IR <= ROMvalue;
					PC <= PC + 1;
					state <= sExecute1;
				when sExecute1=>
					case IR(9 downto 8) is 
					
						--move
						when "00" => 
							case IR(5 downto 4) is
								when "00" =>
									SRC <= ACC;
								when "01" =>
									SRC <= LR;
								when "10" =>
									SRC <= UNSIGNED(IR(3) & IR(3) & IR(3) & IR(3) & IR(3 downto 0));
								when others => 
									SRC <= "11111111";
							end case;
						
						--Binary operations
						when "01" => 
							case IR(4 downto 3) is	
								when "00" =>
									SRC <= ACC;
								when "01" => 
									SRC <= LR;
								when "10" => 
									SRC <= UNSIGNED(IR(1) & IR(1) & IR(1) & IR(1) & IR(1) & IR(1) & IR(1 downto 0));
								when others => 
									SRC <= "11111111";
							end case;
							
						--unconditional branching
						when "10" => 
							PC <= UNSIGNED(IR(3 downto 0));
							
						--conditional branching 
						when "11" =>
							if IR(7) ='0' then
								if ACC = "00000000" then
									PC <= UNSIGNED(IR(3 downto 0));
								end if;
							else 
								if LR = "00000000" then
									PC <= UNSIGNED(IR(3 downto 0));
								end if;
							end if;
						
						when others=>
							NULL;		
									
					end case;
					
				state <= sExecute2;
					
				when sExecute2 =>
					case IR(9 downto 8) is
					
						--move instruction
						when "00" =>
							case IR(7 downto 6) is
								when "00" =>
									ACC <= SRC;
								when "01" =>
									LR <= SRC;
								when "10" =>
									ACC(3 downto 0) <= SRC(3 downto 0);
								when others =>
									ACC(7 downto 4) <= SRC(3 downto 0);
							end case;
							
						--binary operation
						when "01" =>
							case IR(7 downto 5) is
							
								--add operation
								when "000" =>
									if IR(2) = '0' then
										--ACC destination
										ACC <= ACC + SRC;
									else
										--LR destination
										LR <= LR + SRC;
									end if;
									
								--sub operation
								when "001" =>
									if IR(2) = '0' then
										--ACC destination
										ACC <= ACC - SRC;
									else
										--LR destination
										LR <= LR - SRC;
									end if;
								
								--shift left operation
								when "010" => 
									if IR(2) = '0' then 
										--ACC destination
										ACC <= SRC(6 downto 0) & '0';
									else
										--LR destination
										LR <= SRC(6 downto 0) & '0';
									end if;
									
								--shift right maintain sign bit operation
								when "011" =>
									if IR(2) = '0' then 
										--ACC destination
										ACC <= SRC(0) & SRC(7 downto 1);
									else
										--LR destination
										LR <= SRC(0) & SRC(7 downto 1);
									end if;
								
								--XOR operation
								when "100" =>
									if IR(2) = '0' then
										--ACC destination
										ACC <= ACC xor SRC;
									else
										--LR destination
										LR <= LR xor SRC;
									end if;
					
								--AND operation
								when "101" =>
									if IR(2) = '0' then
										--ACC destination
										ACC <= ACC and SRC;
									else
										--LR destination
										LR <= LR and SRC;
									end if;
									
								--rotate left 
								when "110" =>
									if IR(2) = '0' then 
										--ACC destination
										ACC <= SRC(0) & SRC(7 downto 1);
									else
										--LR destination
										LR <= SRC(0) & SRC(7 downto 1);
									end if;
								
								--rotate right
								when others =>
									if IR(2) = '0' then 
										--ACC destination
										ACC <= SRC(6 downto 0) & SRC(7);
									else
										--LR destination
										LR <= SRC(6 downto 0) & SRC(7);
									end if;
								
							end case;
						
						--branch instructions do nothing in sExecute2
						when others => 
							NULL;
					
					end case;
					state <= sFetch;
			end case;
		end if;
	end process;

	
	IRView <= IR;
	lightsig <= std_logic_vector(LR);
	
	--instantiate lightrom component using portmap statement
	pldrom1: pldrom port map(addr => std_logic_vector(PC), data => ROMvalue);

end rtl;

pld2/pldbench.vhd
-- Bruce A. Maxwell
-- Spring 2013
-- CS 232
--
-- test program for the lights circuit
--

library ieee;
use ieee.std_logic_1164.all;
use ieee.numeric_std.all;

entity pldbench is
end entity;

architecture test of pldbench is
  constant num_cycles : integer := 80;

  -- this circuit just needs a clock and a reset
  signal clk : std_logic := '1';
  signal reset : std_logic;

  -- lights component
  component pld2
    port( clk, reset : in std_logic;
          lightsig     : out std_logic_vector(7 downto 0) );
  end component;

  -- output signal
  signal lightsig : std_logic_vector(7 downto 0);

begin

  -- start off with a short reset
  reset <= '0', '1' after 5 ns;

  -- create a clock
  process begin
    for i in 1 to num_cycles loop
      clk <= not clk;
      wait for 5 ns;
      clk <= not clk;
      wait for 5 ns;
    end loop;
    wait;
  end process;

  -- port map the circuit
  L0: pld2 port map( clk, reset, lightsig );

end test;

pld2/pldbench.vcd
$date
  Wed Nov  8 20:12:33 2023
$end
$version
  GHDL v0
$end
$timescale
  1 fs
$end
$scope module standard $end
$upscope $end
$scope module std_logic_1164 $end
$upscope $end
$scope module numeric_std $end
$upscope $end
$scope module pldbench $end
$var reg 1 ! clk $end
$var reg 1 " reset $end
$var reg 8 # lightsig[7:0] $end
$scope module l0 $end
$var reg 1 $ clk $end
$var reg 1 % reset $end
$var reg 8 & lightsig[7:0] $end
$var reg 10 ' irview[9:0] $end
$comment state is not handled $end
$var reg 10 ( ir[9:0] $end
$var reg 4 ) pc[3:0] $end
$var reg 8 * lr[7:0] $end
$var reg 10 + romvalue[9:0] $end
$var reg 8 , acc[7:0] $end
$var reg 8 - src[7:0] $end
$scope module pldrom1 $end
$var reg 4 . addr[3:0] $end
$var reg 10 / data[9:0] $end
$upscope $end
$upscope $end
$upscope $end
$enddefinitions $end
#0
0!
0"
b00000000 #
0$
0%
b00000000 &
b0000000000 '
b0000000000 (
b0000 )
b00000000 *
b0010001000 +
bUUUUUUUU ,
bUUUUUUUU -
b0000 .
b0010001000 /
#5000000
1!
1"
1$
1%
b0010001000 '
b0010001000 (
b0001 )
b0100000000 +
b0001 .
b0100000000 /
#10000000
0!
0$
#15000000
1!
1$
#20000000
0!
0$
#25000000
1!
1$
#30000000
0!
0$
#35000000
1!
1$
b0100000000 '
b0100000000 (
b0010 )
b0111100000 +
b0010 .
b0111100000 /
#40000000
0!
0$
#45000000
1!
1$
#50000000
0!
0$
#55000000
1!
1$
bXXXXXXXX ,
#60000000
0!
0$
#65000000
1!
1$
b0111100000 '
b0111100000 (
b0011 )
b0001000000 +
b0011 .
b0001000000 /
#70000000
0!
0$
#75000000
1!
1$
bXXXXXXXX -
#80000000
0!
0$
#85000000
1!
1$
#90000000
0!
0$
#95000000
1!
1$
b0001000000 '
b0001000000 (
b0100 )
b0111011111 +
b0100 .
b0111011111 /
#100000000
0!
0$
#105000000
1!
1$
#110000000
0!
0$
#115000000
1!
bXXXXXXXX #
1$
bXXXXXXXX &
bXXXXXXXX *
#120000000
0!
0$
#125000000
1!
1$
b0111011111 '
b0111011111 (
b0101 )
b1100000010 +
b0101 .
b1100000010 /
#130000000
0!
0$
#135000000
1!
1$
b11111111 -
#140000000
0!
0$
#145000000
1!
b11111111 #
1$
b11111111 &
b11111111 *
#150000000
0!
0$
#155000000
1!
1$
b1100000010 '
b1100000010 (
b0110 )
b0111111111 +
b0110 .
b0111111111 /
#160000000
0!
0$
#165000000
1!
1$
#170000000
0!
0$
#175000000
1!
1$
#180000000
0!
0$
#185000000
1!
1$
b0111111111 '
b0111111111 (
b0111 )
b0010001000 +
b0111 .
b0010001000 /
#190000000
0!
0$
#195000000
1!
1$
#200000000
0!
0$
#205000000
1!
1$
#210000000
0!
0$
#215000000
1!
1$
b0010001000 '
b0010001000 (
b1000 )
b0101010101 +
b1000 .
b0101010101 /
#220000000
0!
0$
#225000000
1!
1$
bXXXXXXXX -
#230000000
0!
0$
#235000000
1!
1$
#240000000
0!
0$
#245000000
1!
1$
b0101010101 '
b0101010101 (
b1001 )
b0001000000 +
b1001 .
b0001000000 /
#250000000
0!
0$
#255000000
1!
1$
b00000001 -
#260000000
0!
0$
#265000000
1!
b00000010 #
1$
b00000010 &
b00000010 *
#270000000
0!
0$
#275000000
1!
1$
b0001000000 '
b0001000000 (
b1010 )
b0100000000 +
b1010 .
b0100000000 /
#280000000
0!
0$
#285000000
1!
1$
bXXXXXXXX -
#290000000
0!
0$
#295000000
1!
bXXXXXXXX #
1$
bXXXXXXXX &
bXXXXXXXX *
#300000000
0!
0$
#305000000
1!
1$
b0100000000 '
b0100000000 (
b1011 )
b1100001000 +
b1011 .
b1100001000 /
#310000000
0!
0$
#315000000
1!
1$
#320000000
0!
0$
#325000000
1!
1$
#330000000
0!
0$
#335000000
1!
1$
b1100001000 '
b1100001000 (
b1100 )
b1100000001 +
b1100 .
b1100000001 /
#340000000
0!
0$
#345000000
1!
1$
#350000000
0!
0$
#355000000
1!
1$
#360000000
0!
0$
#365000000
1!
1$
b1100000001 '
b1100000001 (
b1101 )
b1111111111 +
b1101 .
b1111111111 /
#370000000
0!
0$
#375000000
1!
1$
#380000000
0!
0$
#385000000
1!
1$
#390000000
0!
0$
#395000000
1!
1$
b1111111111 '
b1111111111 (
b1110 )
b1110 .
#400000000
0!
0$
#405000000
1!
1$
#410000000
0!
0$
#415000000
1!
1$
#420000000
0!
0$
#425000000
1!
1$
b1111 )
b1111 .
#430000000
0!
0$
#435000000
1!
1$
#440000000
0!
0$
#445000000
1!
1$
#450000000
0!
0$
#455000000
1!
1$
b0000 )
b0010001000 +
b0000 .
b0010001000 /
#460000000
0!
0$
#465000000
1!
1$
#470000000
0!
0$
#475000000
1!
1$
#480000000
0!
0$
#485000000
1!
1$
b0010001000 '
b0010001000 (
b0001 )
b0100000000 +
b0001 .
b0100000000 /
#490000000
0!
0$
#495000000
1!
1$
#500000000
0!
0$
#505000000
1!
1$
#510000000
0!
0$
#515000000
1!
1$
b0100000000 '
b0100000000 (
b0010 )
b0111100000 +
b0010 .
b0111100000 /
#520000000
0!
0$
#525000000
1!
1$
#530000000
0!
0$
#535000000
1!
1$
#540000000
0!
0$
#545000000
1!
1$
b0111100000 '
b0111100000 (
b0011 )
b0001000000 +
b0011 .
b0001000000 /
#550000000
0!
0$
#555000000
1!
1$
#560000000
0!
0$
#565000000
1!
1$
#570000000
0!
0$
#575000000
1!
1$
b0001000000 '
b0001000000 (
b0100 )
b0111011111 +
b0100 .
b0111011111 /
#580000000
0!
0$
#585000000
1!
1$
#590000000
0!
0$
#595000000
1!
1$
#600000000
0!
0$
#605000000
1!
1$
b0111011111 '
b0111011111 (
b0101 )
b1100000010 +
b0101 .
b1100000010 /
#610000000
0!
0$
#615000000
1!
1$
b11111111 -
#620000000
0!
0$
#625000000
1!
b11111111 #
1$
b11111111 &
b11111111 *
#630000000
0!
0$
#635000000
1!
1$
b1100000010 '
b1100000010 (
b0110 )
b0111111111 +
b0110 .
b0111111111 /
#640000000
0!
0$
#645000000
1!
1$
#650000000
0!
0$
#655000000
1!
1$
#660000000
0!
0$
#665000000
1!
1$
b0111111111 '
b0111111111 (
b0111 )
b0010001000 +
b0111 .
b0010001000 /
#670000000
0!
0$
#675000000
1!
1$
#680000000
0!
0$
#685000000
1!
1$
#690000000
0!
0$
#695000000
1!
1$
b0010001000 '
b0010001000 (
b1000 )
b0101010101 +
b1000 .
b0101010101 /
#700000000
0!
0$
#705000000
1!
1$
bXXXXXXXX -
#710000000
0!
0$
#715000000
1!
1$
#720000000
0!
0$
#725000000
1!
1$
b0101010101 '
b0101010101 (
b1001 )
b0001000000 +
b1001 .
b0001000000 /
#730000000
0!
0$
#735000000
1!
1$
b00000001 -
#740000000
0!
0$
#745000000
1!
b00000010 #
1$
b00000010 &
b00000010 *
#750000000
0!
0$
#755000000
1!
1$
b0001000000 '
b0001000000 (
b1010 )
b0100000000 +
b1010 .
b0100000000 /
#760000000
0!
0$
#765000000
1!
1$
bXXXXXXXX -
#770000000
0!
0$
#775000000
1!
bXXXXXXXX #
1$
bXXXXXXXX &
bXXXXXXXX *
#780000000
0!
0$
#785000000
1!
1$
b0100000000 '
b0100000000 (
b1011 )
b1100001000 +
b1011 .
b1100001000 /
